orbitlab/__init__.py
orbitlab/__init__.pyi
orbitlab/adapters/__init__.py
orbitlab/adapters/__init__.pyi
orbitlab/adapters/base.py
orbitlab/adapters/base.pyi
orbitlab/adapters/security.py
orbitlab/adapters/security.pyi
orbitlab/core/__init__.py
orbitlab/core/__init__.pyi
orbitlab/core/cache.py
orbitlab/core/cache.pyi
orbitlab/core/config.py
orbitlab/core/config.pyi
orbitlab/core/crypto.py
orbitlab/core/crypto.pyi
orbitlab/core/dynamic_store.py
orbitlab/core/dynamic_store.pyi
orbitlab/core/logger.py
orbitlab/core/logger.pyi
orbitlab/core/mutator.py
orbitlab/core/mutator.pyi
orbitlab/core/registry.py
orbitlab/core/registry.pyi
orbitlab/core/runner.py
orbitlab/core/runner.pyi
orbitlab/core/utils.py
orbitlab/core/utils.pyi
orbitlab/core/validator.py
orbitlab/core/validator.pyi
orbitlab-0.1.7.dist-info/licenses/LICENSE
orbitlab-0.1.7.dist-info/METADATA
orbitlab-0.1.7.dist-info/WHEEL
orbitlab-0.1.7.dist-info/top_level.txt
orbitlab-0.1.7.dist-info/RECORD
