Metadata-Version: 2.4
Name: orbitlab
Version: 0.1.7
Summary: Motor extensible para ejecución segura, validación y versionado de payloads serializados (.dill)
Author-email: Jose Fabian Soltero Escobar <acadyne@gmail.com>
License: BSD-3-Clause
Project-URL: Homepage, https://github.com/acadyne/orbitlab
Project-URL: Repository, https://github.com/acadyne/orbitlab
Project-URL: Issues, https://github.com/acadyne/orbitlab/issues
Requires-Python: >=3.9
License-File: LICENSE
Requires-Dist: dill==0.4.0
Requires-Dist: filelock==3.18.0
Requires-Dist: structlog==25.4.0
Requires-Dist: bcrypt==4.3.0
Requires-Dist: cross-crypto-py==1.1.3
Requires-Dist: pydantic-settings==2.10.1
Provides-Extra: dev
Requires-Dist: pytest; extra == "dev"
Requires-Dist: mypy; extra == "dev"
Requires-Dist: ruff; extra == "dev"
Dynamic: license-file
